AvroLibrary/__init__.py
AvroLibrary/version.py
robotframework_avrolibrary-0.0.3.dist-info/LICENSE
robotframework_avrolibrary-0.0.3.dist-info/METADATA
robotframework_avrolibrary-0.0.3.dist-info/WHEEL
robotframework_avrolibrary-0.0.3.dist-info/top_level.txt
robotframework_avrolibrary-0.0.3.dist-info/RECORD
