Metadata-Version: 2.1
Name: robotframework-avrolibrary
Version: 0.0.3
Summary: Avro library for Robot Framework
Home-page: https://github.com/s4int/robotframework-AvroLibrary
Author: Marcin Mierzejewski
Author-email: <mmierz@gmail.com>
License: Apache License 2.0
Keywords: robotframework testing avro kafka
Platform: any
Classifier: Development Status :: 4 - Beta
Classifier: License :: OSI Approved :: Apache Software License
Classifier: Operating System :: OS Independent
Classifier: Programming Language :: Python
Classifier: Programming Language :: Python :: 2
Classifier: Programming Language :: Python :: 3
Classifier: Topic :: Software Development :: Testing
Classifier: Framework :: Robot Framework
Classifier: Framework :: Robot Framework :: Library
Requires-Dist: robotframework (>=2.6.0)
Requires-Dist: avro
